kaflow/__init__.py
kaflow/_consumer.py
kaflow/applications.py
kaflow/dependencies.py
kaflow/exceptions.py
kaflow/logger.py
kaflow/message.py
kaflow/parameters.py
kaflow/py.typed
kaflow/serializers.py
kaflow/testclient.py
kaflow/typing.py
kaflow/_utils/__init__.py
kaflow/_utils/asyncio.py
kaflow/_utils/inspect.py
kaflow/_utils/overrides.py
kaflow/asyncapi/__init__.py
kaflow/asyncapi/_builder.py
kaflow/asyncapi/docs.py
kaflow/asyncapi/models.py
kaflow-0.2.2.dist-info/METADATA
kaflow-0.2.2.dist-info/WHEEL
kaflow-0.2.2.dist-info/licenses/LICENSE
kaflow-0.2.2.dist-info/RECORD
