Metadata-Version: 2.1
Name: kaflow
Version: 0.2.2
Summary: Python Stream processing backed by Apache Kafka.
Project-URL: Documentation, https://github.com/gabrielmbmb/kaflow#readme
Project-URL: Issues, https://github.com/gabrielmbmb/kaflow/issues
Project-URL: Source, https://github.com/gabrielmbmb/kaflow
Author-email: Gabriel Martin Blazquez <gmartinbdev@gmail.com>
License-Expression: MIT
License-File: LICENSE
Keywords: data,flow,kafka,pipeline,processing,stream
Classifier: Development Status :: 4 - Beta
Classifier: Programming Language :: Python
Classifier: Programming Language :: Python :: 3.8
Classifier: Programming Language :: Python :: 3.9
Classifier: Programming Language :: Python :: 3.10
Classifier: Programming Language :: Python :: 3.11
Classifier: Programming Language :: Python :: Implementation :: CPython
Classifier: Programming Language :: Python :: Implementation :: PyPy
Requires-Python: >=3.8
Requires-Dist: aiokafka>=0.8.0
Requires-Dist: di[anyio]==0.75.2
Requires-Dist: pydantic<2.0.0,>=1.10.0
Requires-Dist: typing-extensions>=4.5.0
Provides-Extra: dev
Requires-Dist: black>=23.1.0; extra == 'dev'
Requires-Dist: coverage[toml]>=7.0.0; extra == 'dev'
Requires-Dist: mypy==0.991; extra == 'dev'
Requires-Dist: pre-commit>=3.0.0; extra == 'dev'
Requires-Dist: pytest>=7.2.0; extra == 'dev'
Requires-Dist: ruff==0.0.257; extra == 'dev'
Requires-Dist: types-protobuf>=3.20.0; extra == 'dev'
Provides-Extra: test
Requires-Dist: fastavro>=1.7.3; extra == 'test'
Requires-Dist: protobuf>=3.20.0; extra == 'test'
